import_wrappers/__init__.py
import_wrappers/_version.py
import_wrappers/optional_dependencies.py
import_wrappers-0.0.2.dist-info/LICENSE
import_wrappers-0.0.2.dist-info/METADATA
import_wrappers-0.0.2.dist-info/WHEEL
import_wrappers-0.0.2.dist-info/top_level.txt
import_wrappers-0.0.2.dist-info/RECORD
